.bumpversion.cfg
.cookiecutterrc
.coveragerc
.editorconfig
.travis.yml
AUTHORS.rst
CHANGELOG.rst
CONTRIBUTING.rst
LICENSE
MANIFEST.in
README.md
appveyor.yml
setup.cfg
setup.py
tox.ini
ci/appveyor-bootstrap.py
ci/appveyor-download.py
ci/appveyor-with-compiler.cmd
ci/bootstrap.py
ci/templates/.travis.yml
ci/templates/appveyor.yml
docs/Makefile
docs/conf.py
docs/index.rst
docs/make.bat
docs/_build/doctrees/environment.pickle
docs/_build/doctrees/index.doctree
docs/_build/doctrees/source/modules.doctree
docs/_build/doctrees/source/prism.annotate.doctree
docs/_build/doctrees/source/prism.cli.doctree
docs/_build/doctrees/source/prism.deconvolute.doctree
docs/_build/doctrees/source/prism.doctree
docs/_build/doctrees/source/prism.extract.doctree
docs/_build/doctrees/source/prism.hmm.doctree
docs/_build/doctrees/source/prism.mixture.doctree
docs/_build/doctrees/source/prism.preprocess.doctree
docs/_build/doctrees/source/prism.proofreading.doctree
docs/_build/doctrees/source/prism.scatter.doctree
docs/_build/doctrees/source/prism.util.doctree
docs/_build/html/.buildinfo
docs/_build/html/genindex.html
docs/_build/html/index.html
docs/_build/html/objects.inv
docs/_build/html/py-modindex.html
docs/_build/html/search.html
docs/_build/html/searchindex.js
docs/_build/html/_images/logo_bgwhite.png
docs/_build/html/_modules/index.html
docs/_build/html/_modules/prism/annotate.html
docs/_build/html/_modules/prism/cli.html
docs/_build/html/_modules/prism/deconvolute.html
docs/_build/html/_modules/prism/extract.html
docs/_build/html/_modules/prism/hmm.html
docs/_build/html/_modules/prism/mixture.html
docs/_build/html/_modules/prism/preprocess.html
docs/_build/html/_modules/prism/proofreading.html
docs/_build/html/_modules/prism/scatter.html
docs/_build/html/_modules/prism/util.html
docs/_build/html/_sources/index.rst.txt
docs/_build/html/_sources/source/modules.rst.txt
docs/_build/html/_sources/source/prism.annotate.rst.txt
docs/_build/html/_sources/source/prism.cli.rst.txt
src/subclone_prism.egg-info/PKG-INFO
src/subclone_prism.egg-info/SOURCES.txt
src/subclone_prism.egg-info/dependency_links.txt
src/subclone_prism.egg-info/entry_points.txt
src/subclone_prism.egg-info/not-zip-safe
src/subclone_prism.egg-info/requires.txt
src/subclone_prism.egg-info/top_level.txt
